lkhandmapping/__init__.py
lkhandtracking/__init__.py
lkhandmapping-0.1.2.dist-info/METADATA
lkhandmapping-0.1.2.dist-info/WHEEL
lkhandmapping-0.1.2.dist-info/top_level.txt
lkhandmapping-0.1.2.dist-info/RECORD
